cvm/__init__.py
cvm/bootstrap.py
cvm/cli.bkup.py
cvm/cli.py
cvm/commands.bkup.py
cvm/commands.py
cvm/commands/__init__.py
cvm/commands/cache_command.py
cvm/commands/command.py
cvm/commands/hook_command.py
cvm/commands/init_command.py
cvm/commands/install_command.py
cvm/commands/list_command.py
cvm/commands/scan_command.py
cvm/commands/use_command.py
cvm/helpers/__init__.py
cvm/helpers/cli.py
cvm/helpers/fs.py
cvm/services/__init__.py
cvm/services/application_service.py
cvm/services/cache_service.py
cvm/services/composer_service.py
cvm/services/config_service.py
cvm/services/github_service.py
cvm/services/shell_service.py
cvm/shells/__init__.py
cvm/shells/shell.py
cvm/shells/shell_bash.py
cvm/shells/shell_zsh.py
composer_version_manager-1.0.7.dist-info/LICENSE.md
composer_version_manager-1.0.7.dist-info/METADATA
composer_version_manager-1.0.7.dist-info/WHEEL
composer_version_manager-1.0.7.dist-info/entry_points.txt
composer_version_manager-1.0.7.dist-info/top_level.txt
composer_version_manager-1.0.7.dist-info/RECORD
