Metadata-Version: 2.1
Name: composer-version-manager
Version: 1.0.7
Summary: UNKNOWN
Home-page: https://github.com/composer-version-manager/cvm
License: MIT
Platform: UNKNOWN
Requires-Python: >=3
Requires-Dist: ansicolors (==1.1.8)
Requires-Dist: argparse-color-formatter (==1.2.2.post2)
Requires-Dist: certifi (==2020.12.5)
Requires-Dist: chardet (==4.0.0)
Requires-Dist: colorama (==0.4.4)
Requires-Dist: idna (==2.10)
Requires-Dist: mypy (==0.790)
Requires-Dist: mypy-extensions (==0.4.3)
Requires-Dist: requests (==2.25.1)
Requires-Dist: six (==1.15.0)
Requires-Dist: typed-ast (==1.4.2)
Requires-Dist: typing-extensions (==3.7.4.3)
Requires-Dist: urllib3 (==1.26.2)
